README.md
setup.py
sch_way2sms.egg-info/PKG-INFO
sch_way2sms.egg-info/SOURCES.txt
sch_way2sms.egg-info/dependency_links.txt
sch_way2sms.egg-info/requires.txt
sch_way2sms.egg-info/top_level.txt
way2sms/__init__.py
way2sms/app.py