Metadata-Version: 2.1
Name: sch-way2sms
Version: 0.0.1
Summary: Send free sms WAY2SMS
Home-page: https://github.com/shubhamc183/way2sms
Author: Shubham Choudhary
Author-email: shubhamc183@gmail.com
License: UNKNOWN
Platform: UNKNOWN
Classifier: Programming Language :: Python :: 3
Classifier: License :: OSI Approved :: MIT License
Classifier: Operating System :: OS Independent
Requires-Python: >=3.6
